special_point/__init__.py
special_point/adic_rational.py
special_point/box_iterate.py
special_point/iter_utils.py
special_point/parameter_iterate.py
specialpointiteration-0.0.2.dist-info/licenses/LICENSE
test/__init__.py
test/test_iter_utils.py
test/test_parameter_iterate.py
specialpointiteration-0.0.2.dist-info/METADATA
specialpointiteration-0.0.2.dist-info/WHEEL
specialpointiteration-0.0.2.dist-info/top_level.txt
specialpointiteration-0.0.2.dist-info/RECORD
