Metadata-Version: 2.4
Name: specialpointiteration
Version: 0.0.2
Summary: Iterate through points in boxes that have some nice denominator structure after a coordinate change
Author-email: Ammar Husain <ammar.s.husain@gmail.com>
Project-URL: Homepage, https://github.com/Cobord/SpecialPointIteration
Project-URL: Bug Tracker, https://github.com/Cobord/SpecialPointIteration/issues
Classifier: Programming Language :: Python :: 3
Classifier: License :: OSI Approved :: GNU General Public License v3 (GPLv3)
Requires-Python: >=3.12
License-File: LICENSE
Dynamic: license-file
